setup.py
DaemonCxt.egg-info/PKG-INFO
DaemonCxt.egg-info/SOURCES.txt
DaemonCxt.egg-info/dependency_links.txt
DaemonCxt.egg-info/top_level.txt
src/daemoncxt/__init__.py
src/daemoncxt/daemon.py
src/daemoncxt/lockfile.py
src/daemoncxt/pidlockfile.py
src/daemoncxt/runner.py
src/daemoncxt/version/__init__.py
src/daemoncxt/version/version_info.py