Metadata-Version: 1.0
Name: DaemonCxt
Version: 1.5.7
Summary: Library to implement a well-behaved Unix daemon process
Home-page: https://github.com/ewiger/daemoncxt
Author: Yauhen Yakimovich
Author-email: eugeny.yakimovitch@gmail.com
License: PSF
Download-URL: https://github.com/ewiger/daemoncxt/tarball/master
Platform: UNKNOWN
